LICENSE
aio_cosmos/__init__.py
aio_cosmos/auth.py
aio_cosmos/client.py
aio_cosmos/http_constants.py
aio_cosmos-0.2.4.dist-info/LICENSE
aio_cosmos-0.2.4.dist-info/WHEEL
aio_cosmos-0.2.4.dist-info/METADATA
aio_cosmos-0.2.4.dist-info/RECORD
