Metadata-Version: 2.1
Name: aio-cosmos
Version: 0.2.4
Summary: Ayncio Client for Azure Cosmos DB
Home-page: https://github.com/calmseas/aio-cosmos
License: MIT
Keywords: azure,cosmos,ayncio,aio,nosql
Author: Grant McDonald
Author-email: calmseasdev@gmail.com
Requires-Python: >=3.7,<4.0
Classifier: License :: OSI Approved :: MIT License
Classifier: Programming Language :: Python :: 3
Classifier: Programming Language :: Python :: 3.10
Classifier: Programming Language :: Python :: 3.7
Classifier: Programming Language :: Python :: 3.8
Classifier: Programming Language :: Python :: 3.9
Requires-Dist: aiohttp[speedups] (>=3.8.0,<4.0.0)
Project-URL: Repository, https://github.com/calmseas/aio-cosmos
